odoo/addons/hr_commission_oca/README.rst
odoo/addons/hr_commission_oca/__init__.py
odoo/addons/hr_commission_oca/__manifest__.py
odoo/addons/hr_commission_oca/i18n/ca.po
odoo/addons/hr_commission_oca/i18n/ca_ES.po
odoo/addons/hr_commission_oca/i18n/es.po
odoo/addons/hr_commission_oca/i18n/hr_commission.pot
odoo/addons/hr_commission_oca/i18n/hr_commission_oca.pot
odoo/addons/hr_commission_oca/i18n/it.po
odoo/addons/hr_commission_oca/i18n/pt_BR.po
odoo/addons/hr_commission_oca/i18n/pt_PT.po
odoo/addons/hr_commission_oca/i18n/tr.po
odoo/addons/hr_commission_oca/models/__init__.py
odoo/addons/hr_commission_oca/models/hr_employee.py
odoo/addons/hr_commission_oca/models/res_partner.py
odoo/addons/hr_commission_oca/models/sale_commission_settlement.py
odoo/addons/hr_commission_oca/readme/CONTRIBUTORS.md
odoo/addons/hr_commission_oca/readme/DESCRIPTION.md
odoo/addons/hr_commission_oca/readme/ROADMAP.md
odoo/addons/hr_commission_oca/static/description/icon.png
odoo/addons/hr_commission_oca/static/description/icon.svg
odoo/addons/hr_commission_oca/static/description/index.html
odoo/addons/hr_commission_oca/tests/__init__.py
odoo/addons/hr_commission_oca/tests/test_hr_commission.py
odoo/addons/hr_commission_oca/views/res_partner_view.xml
odoo/addons/hr_commission_oca/views/sale_commission_settlement_views.xml
odoo_addon_hr_commission_oca-18.0.1.0.0.4.dist-info/METADATA
odoo_addon_hr_commission_oca-18.0.1.0.0.4.dist-info/WHEEL
odoo_addon_hr_commission_oca-18.0.1.0.0.4.dist-info/top_level.txt
odoo_addon_hr_commission_oca-18.0.1.0.0.4.dist-info/RECORD
